MANIFEST.in
data_schema_validate.py
readme.md
setup.py
rx_data_validate.egg-info/PKG-INFO
rx_data_validate.egg-info/SOURCES.txt
rx_data_validate.egg-info/dependency_links.txt
rx_data_validate.egg-info/requires.txt
rx_data_validate.egg-info/top_level.txt
test/test_validator.py