Metadata-Version: 1.0
Name: rx-data-validate
Version: 0.1.0
Summary: Validate Qcumber Data
Home-page: UNKNOWN
Author: Philip Schleihauf
Author-email: uniphil@gmail.com
License: MIT
Platform: UNKNOWN
